genregion/__init__.py
genregion/generate/__init__.py
genregion/generate/gen/__init__.py
genregion/generate/gen/algorithm.py
genregion/generate/gen/cluster.py
genregion/generate/gen/generator.py
genregion/generate/gen/regionalg.py
genregion/generate/gen/segspliter.py
genregion/region/__init__.py
genregion/region/error.py
genregion/region/geometry.py
genregion-0.0.2.dist-info/LICENSE.txt
genregion-0.0.2.dist-info/METADATA
genregion-0.0.2.dist-info/WHEEL
genregion-0.0.2.dist-info/top_level.txt
genregion-0.0.2.dist-info/RECORD
