Metadata-Version: 2.1
Name: genregion
Version: 0.0.2
Summary: Region generation using urban road netwok
Author: Ming Zhang & Yanyan Li
License: UNKNOWN
Platform: UNKNOWN
License-File: LICENSE.txt
Requires-Dist: ordered-set
Requires-Dist: shapely
